extralit_server-0.6.1.dist-info/METADATA
extralit_server-0.6.1.dist-info/WHEEL
extralit_server-0.6.1.dist-info/entry_points.txt
extralit_server-0.6.1.dist-info/licenses/LICENSE
extralit_server-0.6.1.dist-info/licenses/LICENSE_HEADER
extralit_server/__init__.py
extralit_server/__main__.py
extralit_server/_app.py
extralit_server/_version.py
extralit_server/alembic.ini
extralit_server/alembic/env.py
extralit_server/alembic/script.py.mako
extralit_server/alembic/versions/1769ee58fbb4_create_workspaces_users_table.py
extralit_server/alembic/versions/1e629a913727_fix_suggestions_type_enum_values.py
extralit_server/alembic/versions/237f7c674d74_add_status_column_to_records_table.py
extralit_server/alembic/versions/3a8e2f9b5dea_create_questions_table.py
extralit_server/alembic/versions/3fc3c0839959_create_suggestions_table.py
extralit_server/alembic/versions/3ff6484f8b37_add_metadata_column_to_records_table.py
extralit_server/alembic/versions/45a12f74448b_add_distribution_column_to_datasets_table.py
extralit_server/alembic/versions/54d65879a68e_create_document_workflows_table.py
extralit_server/alembic/versions/580a6553186f_add_datasets_users_table.py
extralit_server/alembic/versions/660d6c6b3360_add_metadata_column_to_datasets_table.py
extralit_server/alembic/versions/6ed1b8bf8e08_create_webhooks_table.py
extralit_server/alembic/versions/74694870197c_create_users_table.py
extralit_server/alembic/versions/7552df94427a_added_document_model_and_updated_record_.py
extralit_server/alembic/versions/7850ab5b42d9_create_vectors_settings_table.py
extralit_server/alembic/versions/7cbcccf8b57a_create_metadata_properties_table.py
extralit_server/alembic/versions/7d6b33203390_create_import_history_table.py
extralit_server/alembic/versions/82a5a88a3fa5_create_workspaces_table.py
extralit_server/alembic/versions/84f6b9ff6076_add_last_activity_at_to_datasets_table.py
extralit_server/alembic/versions/8be56284dac0_create_records_table.py
extralit_server/alembic/versions/8c574ada5e5f_update_enum_columns.py
extralit_server/alembic/versions/ae5522b4c674_create_fields_table.py
extralit_server/alembic/versions/b8458008b60e_add_allow_extra_metadata_column_to_datasets_table.py
extralit_server/static/images/help-info/explain.png
extralit_server/static/images/help-info/similarity.png
extralit_server-0.6.1.dist-info/RECORD
