Metadata-Version: 2.1
Name: extralit-server
Version: 0.6.1
Summary: Open-source tool for accurate & fast scientific literature data extraction with LLM and human-in-the-loop.
Keywords: literature-review,data-annotation,artificial-intelligence,machine-learning,human-in-the-loop,mlops
Author-Email: Extralit Labs <extralit.contact@gmail.com>
Maintainer-Email: Extralit Labs <extralit.contact@gmail.com>
License: Apache-2.0
Project-URL: homepage, https://extralit.ai
Project-URL: documentation, https://docs.extralit.ai
Project-URL: repository, https://github.com/extralit/extralit
Requires-Python: >=3.10
Requires-Dist: fastapi~=0.115.0
Requires-Dist: pydantic~=2.9.0
Requires-Dist: pydantic-settings~=2.6.0
Requires-Dist: uvicorn[standard]~=0.32.0
Requires-Dist: opensearch-py~=2.0.0
Requires-Dist: elasticsearch8[async]~=8.7.0
Requires-Dist: brotli-asgi~=1.4.0
Requires-Dist: backoff~=2.2.0
Requires-Dist: alembic~=1.13.0
Requires-Dist: SQLAlchemy~=2.0.0
Requires-Dist: greenlet~=3.1.0
Requires-Dist: aiosqlite==0.20.0
Requires-Dist: aiofiles~=24.1.0
Requires-Dist: PyYAML<6.1.0,>=5.4.1
Requires-Dist: python-jose[cryptography]~=3.3.0
Requires-Dist: bcrypt~=4.2.0
Requires-Dist: python-multipart~=0.0.16
Requires-Dist: httpx~=0.27.0
Requires-Dist: oauthlib~=3.2.0
Requires-Dist: social-auth-core~=4.5.0
Requires-Dist: rq~=2.4.1
Requires-Dist: lazy-loader>=0.4
Requires-Dist: psutil<5.10,~=5.8
Requires-Dist: rich!=13.1.0
Requires-Dist: typer<0.10.0,>=0.6.0
Requires-Dist: packaging>=23.2
Requires-Dist: standardwebhooks>=1.0.0
Requires-Dist: datasets>=3.0.1
Requires-Dist: pillow>=11.3.0
Requires-Dist: huggingface-hub>=0.26.2
Requires-Dist: Jinja2>=3.1.4
Requires-Dist: minio>=7.2.7
Requires-Dist: ocrmypdf>=16.10.4
Requires-Dist: pdf2image>=1.17.0
Requires-Dist: opencv-python-headless>=4.11.0.86
Provides-Extra: postgresql
Requires-Dist: psycopg2~=2.9.0; extra == "postgresql"
Requires-Dist: asyncpg~=0.30.0; extra == "postgresql"
